libed25519.1.2.2.dylib
libed25519.dylib
ed25519_python/__init__.py
ed25519_python/ed25519.py
ed25519_python/libed25519.1.2.2.dylib
ed25519_python/libed25519.dylib
ed25519_python-0.0.11.dist-info/DESCRIPTION.rst
ed25519_python-0.0.11.dist-info/METADATA
ed25519_python-0.0.11.dist-info/RECORD
ed25519_python-0.0.11.dist-info/WHEEL
ed25519_python-0.0.11.dist-info/metadata.json
ed25519_python-0.0.11.dist-info/top_level.txt
tests/__init__.py
