Metadata-Version: 2.0
Name: ed25519-python
Version: 0.0.11
Summary: Python binding for ed25519
Home-page: UNKNOWN
Author: Sonoko Mizuki
Author-email: sonoko@mizuki.io
License: UNKNOWN
Platform: UNKNOWN
